src/__init__.py
src/config.py
src/dataset.py
src/preprocess.py
src/entities/__init__.py
src/entities/data_params.py
src/entities/params.py
src/entities/train_params.py
src/modeling/__init__.py
src/modeling/predict.py
src/modeling/train.py
tests/__init__.py
tests/conftest.py
tests/test_params_loading.py
andrey_misis_mlops2024-0.1.2.dist-info/METADATA
andrey_misis_mlops2024-0.1.2.dist-info/WHEEL
andrey_misis_mlops2024-0.1.2.dist-info/top_level.txt
andrey_misis_mlops2024-0.1.2.dist-info/RECORD
